AnimatedWordCloud/NGrams.py
AnimatedWordCloud/NGrams_monthly.py
AnimatedWordCloud/WordSwarm.py
AnimatedWordCloud/WordSwarm_monthly.py
AnimatedWordCloud/__init__.py
AnimatedWordCloud/animated_word_cloud.py
AnimatedWordCloud/colorer.py
AnimatedWordCloud/preprocessing.py
AnimatedWordCloud/setup.py
AnimatedWordCloud/wsWordObj.py
AnimatedWordCloud/wsWordObj_monthly.py
AnimatedWordCloud/data/themes/default/Vera.ttf
AnimatedWordCloud/data/themes/default/box.down.png
AnimatedWordCloud/data/themes/default/box.hover.png
AnimatedWordCloud/data/themes/default/box.normal.png
AnimatedWordCloud/data/themes/default/button.down.tga
AnimatedWordCloud/data/themes/default/button.hover.tga
AnimatedWordCloud/data/themes/default/button.normal.tga
AnimatedWordCloud/data/themes/default/check.png
AnimatedWordCloud/data/themes/default/checkbox.off.hover.tga
AnimatedWordCloud/data/themes/default/checkbox.off.normal.tga
AnimatedWordCloud/data/themes/default/checkbox.on.hover.tga
AnimatedWordCloud/data/themes/default/checkbox.on.normal.tga
AnimatedWordCloud/data/themes/default/config.txt
AnimatedWordCloud/data/themes/default/console.input.focus.png
AnimatedWordCloud/data/themes/default/console.input.normal.png
AnimatedWordCloud/data/themes/default/console.png
AnimatedWordCloud/data/themes/default/desktop.png
AnimatedWordCloud/data/themes/default/dialog.bar.png
AnimatedWordCloud/data/themes/default/dialog.close.down.tga
AnimatedWordCloud/data/themes/default/dialog.close.hover.tga
AnimatedWordCloud/data/themes/default/dialog.close.normal.tga
AnimatedWordCloud/data/themes/default/dialog.png
AnimatedWordCloud/data/themes/default/dot.down.png
AnimatedWordCloud/data/themes/default/dot.hover.png
AnimatedWordCloud/data/themes/default/dot.normal.png
AnimatedWordCloud/data/themes/default/down.png
AnimatedWordCloud/data/themes/default/filebrowser.folder.png
AnimatedWordCloud/data/themes/default/generate.py
AnimatedWordCloud/data/themes/default/hslider.bar.hover.tga
AnimatedWordCloud-1.0.9.dist-info/LICENSE
AnimatedWordCloud-1.0.9.dist-info/METADATA
AnimatedWordCloud-1.0.9.dist-info/WHEEL
AnimatedWordCloud-1.0.9.dist-info/top_level.txt
AnimatedWordCloud-1.0.9.dist-info/RECORD
