Metadata-Version: 2.1
Name: AnimatedWordCloud
Version: 1.0.9
Summary: Animated version of classic word cloud for time-series text data
Home-page: https://github.com/PetrKorab/AnimatedWordCloud
Author: Petr Koráb
Author-email: xpetrkorab@gmail.com
License: OSI Approved :: Apache Software License
Requires-Python: >=3.8, <3.9
License-File: LICENSE
Requires-Dist: arabica ==1.7.6
Requires-Dist: Box2D ==2.3.10
Requires-Dist: chardet ==3.0.4
Requires-Dist: beautifulsoup4 ==4.12.2
Requires-Dist: openpyxl ==3.1.2
Requires-Dist: pygame ==2.5.0
Requires-Dist: PyQt6 ==6.5.2
Requires-Dist: PyQt6-Qt6 ==6.5.2
Requires-Dist: PyQt6-sip ==13.5.2
Requires-Dist: SQLAlchemy ==1.3.2
Requires-Dist: ftfy ==6.1.1
Requires-Dist: pygame-pgu ==0.21
